{
	"id": "25ac160e-2990-30f7-6f45-fd08e54cd86d",
	"name": "koa-api",
	"description": "",
	"order": [
		"c2ed568a-e242-b6c4-518d-f9ddd02310bb",
		"ae0e7ee1-54f0-39d7-6816-142cbcf705e8",
		"20542929-9f56-45db-c74c-0fdc9a90b363",
		"618bdcd5-2fdd-67a0-9b69-ecc04dd62098",
		"9533c081-5851-68ac-1f93-e8cea0b5ff8c",
		"e5911bc9-3e0c-d30d-9da4-be79be6d7bad",
		"eef20f62-1461-0360-13ff-19bec36d674e",
		"e6925a59-7fc6-3324-d240-2f521c120b26",
		"c79a0214-53dc-fe00-35ce-dc325854b912",
		"8b760dfa-1753-961f-e6ae-df31009ff0b7",
		"d90fc18d-94ab-69b5-0ee8-f559f6ad9e01",
		"7f0f9945-ae27-794e-0bd5-8234b8cf35af",
		"3190d9e8-0ba5-bf2d-8675-48dc046abe18",
		"28592155-7621-f855-c8a9-cd5c8cfe1e1e",
		"70a8ef9f-5037-50c7-773a-b68717a54209",
		"f09f263f-4d59-63f8-9028-00d816de7a3e",
		"73c9de18-36a2-6810-444b-657f6442774e",
		"cac051a1-6cd7-6dda-cff5-5f1555f0b947",
		"65ea1666-0cde-fc74-03cb-ab80aa7e851f",
		"a5091cb2-e714-a01a-a364-dcf9761add34",
		"b6ce6f8a-a3b2-00ed-f148-e45e3d073a9a",
		"16603b26-9d67-b7e1-293b-a9bc48ace79a"
	],
	"folders": [],
	"folders_order": [],
	"timestamp": 1553263724293,
	"owner": 0,
	"public": false,
	"requests": [
		{
			"id": "16603b26-9d67-b7e1-293b-a9bc48ace79a",
			"headers": "",
			"headerData": [],
			"url": "http://localhost:3000/student-hour/list",
			"queryParams": [],
			"pathVariables": {},
			"pathVariableData": [],
			"preRequestScript": null,
			"method": "POST",
			"collectionId": "25ac160e-2990-30f7-6f45-fd08e54cd86d",
			"data": null,
			"dataMode": "params",
			"name": "学时课时的统计",
			"description": "",
			"descriptionFormat": "html",
			"time": 1553327681153,
			"version": 2,
			"responses": [],
			"tests": null,
			"currentHelper": "normal",
			"helperAttributes": {}
		},
		{
			"id": "20542929-9f56-45db-c74c-0fdc9a90b363",
			"headers": "Content-Type: application/json\n",
			"headerData": [
				{
					"key": "Content-Type",
					"value": "application/json",
					"description": "",
					"enabled": true
				}
			],
			"url": "http://localhost:3000/student/add",
			"queryParams": [],
			"preRequestScript": null,
			"pathVariables": {},
			"pathVariableData": [],
			"method": "POST",
			"data": [],
			"dataMode": "raw",
			"version": 2,
			"tests": null,
			"currentHelper": "normal",
			"helperAttributes": {},
			"time": 1553270795408,
			"name": "添加学生",
			"description": "",
			"collectionId": "25ac160e-2990-30f7-6f45-fd08e54cd86d",
			"responses": [],
			"rawModeData": "{\r\n    \"name\": \"学生\",\r\n    \"birthday\": \"2000-12-12\",\r\n    \"sex\": 1,\r\n    \"age\": 19,\r\n    \"contacts\": \"爸爸\",\r\n    \"phone\": \"11111\",\r\n    \"province\": \"省\",\r\n    \"city\": \"市\",\r\n    \"region\": \"\",\r\n    \"address\": \"\",\r\n    \"teacherId\": \"teacherId\",\r\n    \"status\": 1,\r\n    \"desc\": \"描述\"\r\n}",
			"collection_id": "25ac160e-2990-30f7-6f45-fd08e54cd86d"
		},
		{
			"id": "28592155-7621-f855-c8a9-cd5c8cfe1e1e",
			"headers": "",
			"headerData": [],
			"url": "http://localhost:3000/course/5c95a1277e55e11d5a893e86",
			"queryParams": [],
			"pathVariables": {},
			"pathVariableData": [],
			"preRequestScript": null,
			"method": "GET",
			"collectionId": "25ac160e-2990-30f7-6f45-fd08e54cd86d",
			"data": null,
			"dataMode": "params",
			"name": "课程详情",
			"description": "",
			"descriptionFormat": "html",
			"time": 1553310117187,
			"version": 2,
			"responses": [],
			"tests": null,
			"currentHelper": "normal",
			"helperAttributes": {}
		},
		{
			"id": "3190d9e8-0ba5-bf2d-8675-48dc046abe18",
			"headers": "",
			"headerData": [],
			"url": "http://localhost:3000/course/list",
			"queryParams": [],
			"pathVariables": {},
			"pathVariableData": [],
			"preRequestScript": null,
			"method": "POST",
			"collectionId": "25ac160e-2990-30f7-6f45-fd08e54cd86d",
			"data": null,
			"dataMode": "params",
			"name": "课程列表",
			"description": "",
			"descriptionFormat": "html",
			"time": 1553310070212,
			"version": 2,
			"responses": [],
			"tests": null,
			"currentHelper": "normal",
			"helperAttributes": {}
		},
		{
			"id": "618bdcd5-2fdd-67a0-9b69-ecc04dd62098",
			"headers": "",
			"headerData": [],
			"url": "http://localhost:3000/student/5c94f8b887fbda2a4c3fc1c7",
			"queryParams": [],
			"preRequestScript": null,
			"pathVariables": {},
			"pathVariableData": [],
			"method": "GET",
			"data": null,
			"dataMode": "params",
			"version": 2,
			"tests": null,
			"currentHelper": "normal",
			"helperAttributes": {},
			"time": 1553270793556,
			"name": "查看学生的详情",
			"description": "",
			"collectionId": "25ac160e-2990-30f7-6f45-fd08e54cd86d",
			"responses": [],
			"collection_id": "25ac160e-2990-30f7-6f45-fd08e54cd86d"
		},
		{
			"id": "65ea1666-0cde-fc74-03cb-ab80aa7e851f",
			"headers": "",
			"headerData": [],
			"url": "http://localhost:3000/class-hour/5c95ac8f561585287838d7d2",
			"queryParams": [],
			"pathVariables": {},
			"pathVariableData": [],
			"preRequestScript": null,
			"method": "GET",
			"collectionId": "25ac160e-2990-30f7-6f45-fd08e54cd86d",
			"data": null,
			"dataMode": "params",
			"name": "学时详情",
			"description": "",
			"descriptionFormat": "html",
			"time": 1553313108578,
			"version": 2,
			"responses": [],
			"tests": null,
			"currentHelper": "normal",
			"helperAttributes": {}
		},
		{
			"id": "70a8ef9f-5037-50c7-773a-b68717a54209",
			"headers": "Content-Type: application/json\n",
			"headerData": [
				{
					"key": "Content-Type",
					"value": "application/json",
					"description": "",
					"enabled": true
				}
			],
			"url": "http://localhost:3000/course/5c95a1277e55e11d5a893e86",
			"queryParams": [],
			"pathVariables": {},
			"pathVariableData": [],
			"preRequestScript": null,
			"method": "PUT",
			"collectionId": "25ac160e-2990-30f7-6f45-fd08e54cd86d",
			"data": [],
			"dataMode": "raw",
			"name": "修改课程",
			"description": "",
			"descriptionFormat": "html",
			"time": 1553310186942,
			"version": 2,
			"responses": [],
			"tests": null,
			"currentHelper": "normal",
			"helperAttributes": {},
			"rawModeData": "{\"name\": \"新的学生课程\"}"
		},
		{
			"id": "73c9de18-36a2-6810-444b-657f6442774e",
			"headers": "Content-Type: application/json\n",
			"headerData": [
				{
					"key": "Content-Type",
					"value": "application/json",
					"description": "",
					"enabled": true
				}
			],
			"url": "http://localhost:3000/class-hour/add",
			"queryParams": [],
			"pathVariables": {},
			"pathVariableData": [],
			"preRequestScript": null,
			"method": "POST",
			"collectionId": "25ac160e-2990-30f7-6f45-fd08e54cd86d",
			"data": [],
			"dataMode": "raw",
			"name": "添加课时",
			"description": "",
			"descriptionFormat": "html",
			"time": 1553312963283,
			"version": 2,
			"responses": [],
			"tests": null,
			"currentHelper": "normal",
			"helperAttributes": {},
			"rawModeData": "{\n    \"name\": \"学生家长\",\n    \"num\": 3,\n    \"studentId\": \"studentId\",\n    \"type\": 1,\n    \"classTypes\": 1,\n    \"amount\": 100,\n    \"status\": 1,\n    \"desc\": \"添加学时\"\n}"
		},
		{
			"id": "7f0f9945-ae27-794e-0bd5-8234b8cf35af",
			"headers": "Content-Type: application/json\n",
			"headerData": [
				{
					"key": "Content-Type",
					"value": "application/json",
					"description": "",
					"enabled": true
				}
			],
			"url": "http://localhost:3000/course/add",
			"queryParams": [],
			"pathVariables": {},
			"pathVariableData": [],
			"preRequestScript": "",
			"method": "POST",
			"collectionId": "25ac160e-2990-30f7-6f45-fd08e54cd86d",
			"data": [],
			"dataMode": "raw",
			"name": "添加课程",
			"description": "",
			"descriptionFormat": "html",
			"time": 1553310053018,
			"version": 2,
			"responses": [],
			"tests": "tests[\"response code is 401\"] = responseCode.code === 401;\ntests[\"response has WWW-Authenticate header\"] = (postman.getResponseHeader('WWW-Authenticate'));\n\nvar authenticateHeader = postman.getResponseHeader('WWW-Authenticate'),\n    realmStart = authenticateHeader.indexOf('\"',authenticateHeader.indexOf(\"realm\")) + 1 ,\n    realmEnd = authenticateHeader.indexOf('\"',realmStart),\n    realm = authenticateHeader.slice(realmStart,realmEnd),\n    nonceStart = authenticateHeader.indexOf('\"',authenticateHeader.indexOf(\"nonce\")) + 1,\n    nonceEnd = authenticateHeader.indexOf('\"',nonceStart),\n    nonce = authenticateHeader.slice(nonceStart,nonceEnd);\n    \npostman.setGlobalVariable('echo_digest_realm', realm);\npostman.setGlobalVariable('echo_digest_nonce', nonce);",
			"currentHelper": "normal",
			"helperAttributes": {},
			"rawModeData": "{\n    \"name\": \"学生的课程\",\n    \"teacherId\": \"teacherId\",\n    \"status\": 1,\n    \"day\": 1,\n    \"time\": 1,\n    \"startDate\": 1,\n    \"endDate\": 1,\n    \"desc\": \"课程的简介\"\n}"
		},
		{
			"id": "8b760dfa-1753-961f-e6ae-df31009ff0b7",
			"headers": "Content-Type: application/json\n",
			"headerData": [
				{
					"key": "Content-Type",
					"value": "application/json",
					"description": "",
					"enabled": true
				}
			],
			"url": "http://localhost:3000/teacher/5c95cd87194aee325dd3e014",
			"queryParams": [],
			"preRequestScript": null,
			"pathVariables": {},
			"pathVariableData": [],
			"method": "PUT",
			"data": [],
			"dataMode": "raw",
			"version": 2,
			"tests": null,
			"currentHelper": "normal",
			"helperAttributes": {},
			"time": 1553324300429,
			"name": "修改老师",
			"description": "",
			"collectionId": "25ac160e-2990-30f7-6f45-fd08e54cd86d",
			"responses": [],
			"rawModeData": "{\r\n  \"name\": \"xin老师\",\r\n  \"desc\": \"添加描述111111\"\r\n}"
		},
		{
			"id": "9533c081-5851-68ac-1f93-e8cea0b5ff8c",
			"headers": "Content-Type: application/json\n",
			"headerData": [
				{
					"key": "Content-Type",
					"value": "application/json",
					"description": "",
					"enabled": true
				}
			],
			"url": "http://localhost:3000/student/5c94f8b887fbda2a4c3fc1c7",
			"queryParams": [],
			"preRequestScript": null,
			"pathVariables": {},
			"pathVariableData": [],
			"method": "PUT",
			"data": [],
			"dataMode": "raw",
			"version": 2,
			"tests": null,
			"currentHelper": "normal",
			"helperAttributes": {},
			"time": 1553269616744,
			"name": "修改学生的详情",
			"description": "",
			"collectionId": "25ac160e-2990-30f7-6f45-fd08e54cd86d",
			"responses": [],
			"rawModeData": "{\r\n    \"name\": \"xin111学生\",\r\n    \"birthday\": \"2000-12-12\",\r\n    \"age\": 9\r\n}",
			"collection_id": "25ac160e-2990-30f7-6f45-fd08e54cd86d"
		},
		{
			"id": "a5091cb2-e714-a01a-a364-dcf9761add34",
			"headers": "",
			"headerData": [],
			"url": "http://localhost:3000/class-hour/5c95ac8f561585287838d7d2",
			"queryParams": [],
			"pathVariables": {},
			"pathVariableData": [],
			"preRequestScript": null,
			"method": "DELETE",
			"collectionId": "25ac160e-2990-30f7-6f45-fd08e54cd86d",
			"data": null,
			"dataMode": "params",
			"name": "删除学时",
			"description": "",
			"descriptionFormat": "html",
			"time": 1553313208313,
			"version": 2,
			"responses": [],
			"tests": null,
			"currentHelper": "normal",
			"helperAttributes": {}
		},
		{
			"id": "ae0e7ee1-54f0-39d7-6816-142cbcf705e8",
			"headers": "Content-Type: application/json\n",
			"headerData": [
				{
					"key": "Content-Type",
					"value": "application/json",
					"description": "",
					"enabled": true
				}
			],
			"url": "http://localhost:3000/student/list",
			"queryParams": [],
			"preRequestScript": null,
			"pathVariables": {},
			"pathVariableData": [],
			"method": "POST",
			"data": [],
			"dataMode": "raw",
			"tests": null,
			"currentHelper": "normal",
			"helperAttributes": {},
			"time": 1553264144200,
			"name": "查看学生列表",
			"description": "",
			"collectionId": "25ac160e-2990-30f7-6f45-fd08e54cd86d",
			"responses": [],
			"rawModeData": "",
			"collection_id": "25ac160e-2990-30f7-6f45-fd08e54cd86d"
		},
		{
			"id": "b6ce6f8a-a3b2-00ed-f148-e45e3d073a9a",
			"headers": "Content-Type: application/json\n",
			"headerData": [
				{
					"key": "Content-Type",
					"value": "application/json",
					"description": "",
					"enabled": true
				}
			],
			"url": "http://localhost:3000/class-hour/5c95ac8f561585287838d7d2",
			"queryParams": [],
			"pathVariables": {},
			"pathVariableData": [],
			"preRequestScript": null,
			"method": "PUT",
			"collectionId": "25ac160e-2990-30f7-6f45-fd08e54cd86d",
			"data": [],
			"dataMode": "raw",
			"name": "修改学时",
			"description": "",
			"descriptionFormat": "html",
			"time": 1553313227402,
			"version": 2,
			"responses": [],
			"tests": null,
			"currentHelper": "normal",
			"helperAttributes": {},
			"rawModeData": "{\n    \"name\": \"学生家长1\",\n    \"num\": 31\n}"
		},
		{
			"id": "c2ed568a-e242-b6c4-518d-f9ddd02310bb",
			"headers": "Authorization: eyJhbGciOiJIUzI1NiIsInR5cCI6IkpXVCJ9.eyJ1aWQiOjEyMywibmFtZSI6IjExMTEiLCJpYXQiOjE1NTE4Nzg1MzYsImV4cCI6MTU1MTg4MjEzNn0.HfSaXW88j64K7Cd1tl6FNR_CtAKHrntYDJGIGp5B5DQ\nContent-Type: application/json\n",
			"headerData": [
				{
					"key": "Authorization",
					"value": "eyJhbGciOiJIUzI1NiIsInR5cCI6IkpXVCJ9.eyJ1aWQiOjEyMywibmFtZSI6IjExMTEiLCJpYXQiOjE1NTE4Nzg1MzYsImV4cCI6MTU1MTg4MjEzNn0.HfSaXW88j64K7Cd1tl6FNR_CtAKHrntYDJGIGp5B5DQ",
					"description": "",
					"enabled": true
				},
				{
					"key": "Content-Type",
					"value": "application/json",
					"description": "",
					"enabled": true
				}
			],
			"url": "localhost:3000/v1/auth/login",
			"queryParams": [],
			"pathVariables": {},
			"pathVariableData": [],
			"preRequestScript": null,
			"method": "POST",
			"collectionId": "25ac160e-2990-30f7-6f45-fd08e54cd86d",
			"data": [],
			"dataMode": "raw",
			"name": "登录",
			"description": "登录",
			"descriptionFormat": "html",
			"time": 1553263778095,
			"version": 2,
			"responses": [],
			"tests": null,
			"currentHelper": "normal",
			"helperAttributes": {},
			"rawModeData": "{\"name\": \"yangpu\", \"password\": \"12345\"}",
			"collection_id": "25ac160e-2990-30f7-6f45-fd08e54cd86d"
		},
		{
			"id": "c79a0214-53dc-fe00-35ce-dc325854b912",
			"headers": "",
			"headerData": [],
			"url": "http://localhost:3000/teacher/5c95035e4e2878415c46a2a5",
			"queryParams": [],
			"pathVariables": {},
			"pathVariableData": [],
			"preRequestScript": null,
			"method": "GET",
			"collectionId": "25ac160e-2990-30f7-6f45-fd08e54cd86d",
			"data": null,
			"dataMode": "params",
			"name": "老师详情",
			"description": "",
			"descriptionFormat": "html",
			"time": 1553270527389,
			"version": 2,
			"responses": [],
			"tests": null,
			"currentHelper": "normal",
			"helperAttributes": {},
			"collection_id": "25ac160e-2990-30f7-6f45-fd08e54cd86d"
		},
		{
			"id": "cac051a1-6cd7-6dda-cff5-5f1555f0b947",
			"headers": "",
			"headerData": [],
			"url": "http://localhost:3000/class-hour/list",
			"queryParams": [],
			"pathVariables": {},
			"pathVariableData": [],
			"preRequestScript": null,
			"method": "POST",
			"collectionId": "25ac160e-2990-30f7-6f45-fd08e54cd86d",
			"data": null,
			"dataMode": "params",
			"name": "课时列表",
			"description": "",
			"descriptionFormat": "html",
			"time": 1553313044090,
			"version": 2,
			"responses": [],
			"tests": null,
			"currentHelper": "normal",
			"helperAttributes": {}
		},
		{
			"id": "d90fc18d-94ab-69b5-0ee8-f559f6ad9e01",
			"headers": "",
			"headerData": [],
			"url": "http://localhost:3000/teacher/5c95035e4e2878415c46a2a5",
			"queryParams": [],
			"pathVariables": {},
			"pathVariableData": [],
			"preRequestScript": null,
			"method": "DELETE",
			"collectionId": "25ac160e-2990-30f7-6f45-fd08e54cd86d",
			"data": null,
			"dataMode": "params",
			"name": "删除老师",
			"description": "",
			"descriptionFormat": "html",
			"time": 1553270776566,
			"version": 2,
			"responses": [],
			"tests": null,
			"currentHelper": "normal",
			"helperAttributes": {},
			"collection_id": "25ac160e-2990-30f7-6f45-fd08e54cd86d"
		},
		{
			"id": "e5911bc9-3e0c-d30d-9da4-be79be6d7bad",
			"headers": "",
			"headerData": [],
			"url": "http://localhost:3000/student/5c94edc45210d5077c3a6481",
			"queryParams": [],
			"preRequestScript": null,
			"pathVariables": {},
			"pathVariableData": [],
			"method": "DELETE",
			"data": null,
			"dataMode": "params",
			"version": 2,
			"tests": null,
			"currentHelper": "normal",
			"helperAttributes": {},
			"time": 1553269610523,
			"name": "删除学生",
			"description": "",
			"collectionId": "25ac160e-2990-30f7-6f45-fd08e54cd86d",
			"responses": [],
			"collection_id": "25ac160e-2990-30f7-6f45-fd08e54cd86d"
		},
		{
			"id": "e6925a59-7fc6-3324-d240-2f521c120b26",
			"headers": "Content-Type: application/json\n",
			"headerData": [
				{
					"key": "Content-Type",
					"value": "application/json",
					"description": "",
					"enabled": true
				}
			],
			"url": "http://localhost:3000/teacher/list",
			"queryParams": [],
			"pathVariables": {},
			"pathVariableData": [],
			"preRequestScript": null,
			"method": "POST",
			"collectionId": "25ac160e-2990-30f7-6f45-fd08e54cd86d",
			"data": [],
			"dataMode": "raw",
			"name": "查找老师列表",
			"description": "",
			"descriptionFormat": "html",
			"time": 1553270371809,
			"version": 2,
			"responses": [],
			"tests": null,
			"currentHelper": "normal",
			"helperAttributes": {},
			"rawModeData": "{}",
			"collection_id": "25ac160e-2990-30f7-6f45-fd08e54cd86d"
		},
		{
			"id": "eef20f62-1461-0360-13ff-19bec36d674e",
			"headers": "Content-Type: application/json\n",
			"headerData": [
				{
					"key": "Content-Type",
					"value": "application/json",
					"description": "",
					"enabled": true
				}
			],
			"url": "http://localhost:3000/teacher/add",
			"queryParams": [],
			"pathVariables": {},
			"pathVariableData": [],
			"preRequestScript": null,
			"method": "POST",
			"collectionId": "25ac160e-2990-30f7-6f45-fd08e54cd86d",
			"data": [],
			"dataMode": "raw",
			"name": "添加老师",
			"description": "",
			"descriptionFormat": "html",
			"time": 1553269638395,
			"version": 2,
			"responses": [],
			"tests": null,
			"currentHelper": "normal",
			"helperAttributes": {},
			"rawModeData": "{\r\n  \"name\": \"老师\",\r\n  \"birthday\": \"2000-12-12\",\r\n  \"sex\": 1,\r\n  \"age\": 19,\r\n  \"phone\": \"11111\",\r\n  \"province\": \"省\",\r\n  \"city\": \"市\",\r\n  \"region\": \"\",\r\n  \"address\": \"\",\r\n  \"status\": 1,\r\n  \"desc\": \"添加描述\"\r\n}",
			"collection_id": "25ac160e-2990-30f7-6f45-fd08e54cd86d"
		},
		{
			"id": "f09f263f-4d59-63f8-9028-00d816de7a3e",
			"headers": "",
			"headerData": [],
			"url": "http://localhost:3000/course/5c95a1277e55e11d5a893e86",
			"queryParams": [],
			"pathVariables": {},
			"pathVariableData": [],
			"preRequestScript": null,
			"method": "DELETE",
			"collectionId": "25ac160e-2990-30f7-6f45-fd08e54cd86d",
			"data": null,
			"dataMode": "params",
			"name": "删除课程",
			"description": "",
			"descriptionFormat": "html",
			"time": 1553310238749,
			"version": 2,
			"responses": [],
			"tests": null,
			"currentHelper": "normal",
			"helperAttributes": {}
		}
	]
}